bitscreen_updater/__init__.py
bitscreen_updater/__main__.py
bitscreen_updater/daemon.py
bitscreen_updater/exceptions.py
bitscreen_updater/filter_checker.py
bitscreen_updater/provider_session.py
bitscreen_updater/task_runner.py
bitscreen_updater/updater.py
bitscreen_updater-0.1.12.dist-info/METADATA
bitscreen_updater-0.1.12.dist-info/WHEEL
bitscreen_updater-0.1.12.dist-info/dependency_links.txt
bitscreen_updater-0.1.12.dist-info/entry_points.txt
bitscreen_updater-0.1.12.dist-info/top_level.txt
bitscreen_updater-0.1.12.dist-info/RECORD
