Metadata-Version: 2.1
Name: bitscreen-updater
Version: 0.1.12
Summary: A BitScreen daemon that keeps track of all blocked CIDs and checks deal requests through a socket
Home-page: UNKNOWN
Author: Keyko
License: UNKNOWN
Platform: UNKNOWN
Classifier: License :: OSI Approved :: MIT License
Classifier: Programming Language :: Python :: 2.7
Classifier: Programming Language :: Python :: 3
Classifier: Programming Language :: Python :: 3.7
Requires-Python: >=3.0
Requires-Dist: requests ==2.26.0
Requires-Dist: web3 ==5.23.1
Requires-Dist: tabulate ==0.8.9
Requires-Dist: dashing ==0.1.0
Requires-Dist: py-crypto-hd-wallet ==0.13.0
Requires-Dist: pycryptodome ==3.11.0
Requires-Dist: zmq
